{
  "id": "emergency-door-threshold-water-seal-fix-deskati-town",
  "slug": "epigousa-episkevi-steganopoiisis-katofliou-portas-deskati-town",
  "nameGr": "Επείγουσα Επισκευή Στεγανοποίησης Κατωφλιού Πόρτας στη Δεσκάτη",
  "nameEn": "Emergency Door Threshold Water Seal Fix in Δεσκάτη",
  "categoryId": "locksmiths",
  "categorySlug": "kleidarades",
  "intent": "Επείγουσα επισκευή στεγανοποίησης κατωφλιού πόρτας στη Δεσκάτη για αποφυγή εισροής νερού και αέρα. SEO intent: «μπάζει νερά η πόρτα Δεσκάτη».",
  "typicalDuration": "20-90 λεπτά",
  "priceRangeEUR": "45-170€",
  "demand": "high",
  "keywords": [
    "μπάζει νερά η πόρτα Δεσκάτη",
    "στεγανοποίηση κατωφλιού πόρτας",
    "κλειδαράς ρύθμιση εισόδου",
    "επισκευή weatherstrip πόρτας",
    "πόρτα εισόδου αέρας λύση"
  ],
  "status": "researched"
}