{
  "id": "emergency-shutter-guide-brush-replacement-kria-vrysi",
  "slug": "epigousa-antikatastasi-vourtsas-odigou-rolou-kria-vrysi",
  "nameGr": "Επείγουσα Αντικατάσταση Βούρτσας Οδηγού Ρολού στην Κρύα Βρύση",
  "nameEn": "Emergency Shutter Guide Brush Replacement in Κρύα Βρύση",
  "categoryId": "aluminum-frames",
  "categorySlug": "koufomata-alouminiou",
  "intent": "Επείγουσα αντικατάσταση βούρτσας οδηγού ρολού στην Κρύα Βρύση για ομαλή κύλιση και προστασία από αέρα/σκόνη.",
  "typicalDuration": "20-90 λεπτά",
  "priceRangeEUR": "50-180€",
  "demand": "high",
  "keywords": [
    "Κρύα Βρύση επείγον",
    "Επείγουσα Κρύα Βρύση",
    "άμεση εξυπηρέτηση",
    "service κατοικίας",
    "τοπικός τεχνικός"
  ],
  "status": "researched"
}