{
  "id": "emergency-shutter-drive-hub-ring-seat-fix-mikri-doxipara",
  "slug": "epigousa-episkevi-edras-daktyliou-kentrou-kinisis-rolou-mikri-doxipara",
  "nameGr": "Επείγουσα Επισκευή Έδρας Δακτυλίου Κέντρου Κίνησης Ρολού στη Μικρή Δοξιπάρα",
  "nameEn": "Emergency Shutter Drive Hub Ring Seat Fix in Μικρή Δοξιπάρα",
  "categoryId": "aluminum-frames",
  "categorySlug": "koufomata-alouminiou",
  "intent": "Επείγουσα επισκευή έδρας δακτυλίου κέντρου κίνησης ρολού στη Μικρή Δοξιπάρα για ομαλή λειτουργία χωρίς μπλοκάρισμα.",
  "typicalDuration": "20-90 λεπτά",
  "priceRangeEUR": "50-180€",
  "demand": "high",
  "keywords": [
    "Μικρή Δοξιπάρα επείγον",
    "άμεση εξυπηρέτηση",
    "τοπικός τεχνικός",
    "service κατοικίας",
    "επισκευή τώρα"
  ],
  "status": "researched"
}