{
  "id": "emergency-shutter-drive-wheel-pin-fix-agios-georgios-amfiloxias",
  "slug": "epigousa-episkevi-pin-troxou-kinisis-rolou-agios-georgios-amfiloxias",
  "nameGr": "Επείγουσα Επισκευή Pin Τροχού Κίνησης Ρολού στον Άγιο Γεώργιο Αμφιλοχίας",
  "nameEn": "Emergency Shutter Drive Wheel Pin Fix in Άγιος Γεώργιος Αμφιλοχίας",
  "categoryId": "aluminum-frames",
  "categorySlug": "koufomata-alouminiou",
  "intent": "Επείγουσα επισκευή pin τροχού κίνησης ρολού στον Άγιο Γεώργιο Αμφιλοχίας για ομαλή κύλιση χωρίς μπλοκάρισμα.",
  "typicalDuration": "20-90 λεπτά",
  "priceRangeEUR": "50-180€",
  "demand": "high",
  "keywords": [
    "Άγιος Γεώργιος Αμφιλοχίας επείγον",
    "άμεση εξυπηρέτηση",
    "τοπικός τεχνικός",
    "service κατοικίας",
    "επισκευή τώρα"
  ],
  "status": "researched"
}