{
  "id": "emergency-entry-door-lock-striker-pocket-adjust-petra-zagoriou",
  "slug": "epigousa-rythmisi-thikis-striker-kleidarias-portas-eisodou-petra-zagoriou",
  "nameGr": "Επείγουσα Ρύθμιση Θήκης Striker Κλειδαριάς Πόρτας Εισόδου στην Πέτρα Ζαγορίου",
  "nameEn": "Emergency Entry Door Lock Striker Pocket Adjust in Πέτρα Ζαγορίου",
  "categoryId": "locksmiths",
  "categorySlug": "kleidarades",
  "intent": "Επείγουσα ρύθμιση θήκης striker κλειδαριάς πόρτας εισόδου στην Πέτρα Ζαγορίου για ομαλό και ασφαλές κλείδωμα.",
  "typicalDuration": "20-60 λεπτά",
  "priceRangeEUR": "50-180€",
  "demand": "high",
  "keywords": [
    "Πέτρα Ζαγορίου επείγον",
    "άμεση εξυπηρέτηση",
    "τοπικός τεχνικός",
    "service κατοικίας",
    "επισκευή τώρα"
  ],
  "status": "researched"
}