{
  "id": "emergency-entry-door-bolt-throw-adjustment-steni-vlasias",
  "slug": "epigousa-rythmisi-diadromis-syrthikou-kleidarias-eisodou-steni-vlasias",
  "nameGr": "Επείγουσα Ρύθμιση Διαδρομής Σύρτη Κλειδαριάς Εισόδου στη Στενή Βλασίας",
  "nameEn": "Emergency Entry Door Bolt Throw Adjustment in Στενή Βλασίας",
  "categoryId": "locksmiths",
  "categorySlug": "kleidarades",
  "intent": "Επείγουσα ρύθμιση διαδρομής σύρτη κλειδαριάς εισόδου στη Στενή Βλασίας για άμεσο ασφαλές κλείδωμα.",
  "typicalDuration": "20-60 λεπτά",
  "priceRangeEUR": "50-180€",
  "demand": "high",
  "keywords": [
    "Στενή Βλασίας επείγον",
    "άμεση εξυπηρέτηση",
    "τοπικός τεχνικός",
    "service κατοικίας",
    "επισκευή τώρα"
  ],
  "status": "researched"
}