{
  "id": "home-voltage-spike-protector-installation-karpathos",
  "slug": "egkatastasi-prostasias-ypentasis-spitiou-karpathos",
  "nameGr": "Εγκατάσταση Προστασίας Υπέρτασης Κατοικίας στην Κάρπαθο",
  "nameEn": "Home Voltage Spike Protector Installation in Κάρπαθος",
  "categoryId": "electricians",
  "categorySlug": "ilektrologoi",
  "intent": "Εγκατάσταση προστασίας υπέρτασης στην Κάρπαθο στον πίνακα για προστασία συσκευών από αιχμές τάσης και κεραυνούς. SEO intent: στοχεύει high-intent queries «προστασία υπέρτασης σπίτι Κάρπαθος».",
  "typicalDuration": "1-3 ώρες",
  "priceRangeEUR": "110-420€",
  "demand": "high",
  "keywords": [
    "προστασία υπέρτασης σπίτι Κάρπαθος",
    "αντικεραυνική προστασία πίνακα Κάρπαθος",
    "ηλεκτρολόγος surge protector",
    "προστασία συσκευών από τάση",
    "SPD εγκατάσταση"
  ],
  "status": "researched"
}