{
  "id": "seasonal-heating-manifold-air-bleed-tune-loutra-eleftheron",
  "slug": "epochiaki-rythmisi-exaerosis-syllekti-thermansis-loutra-eleftheron",
  "nameGr": "Εποχική Ρύθμιση Εξαέρωσης Συλλέκτη Θέρμανσης στα Λουτρά Ελευθερών",
  "nameEn": "Seasonal Heating Manifold Air Bleed Tune in Λουτρά Ελευθερών",
  "categoryId": "hvac-technicians",
  "categorySlug": "techniki-klimatismou",
  "intent": "Εποχική ρύθμιση εξαέρωσης συλλέκτη θέρμανσης στα Λουτρά Ελευθερών για καλύτερη κυκλοφορία και αποδοτικότητα.",
  "typicalDuration": "30-120 λεπτά",
  "priceRangeEUR": "45-170€",
  "demand": "high",
  "keywords": [
    "Λουτρά Ελευθερών επείγον",
    "άμεση εξυπηρέτηση",
    "τοπικός τεχνικός",
    "service κατοικίας",
    "επισκευή τώρα"
  ],
  "status": "researched"
}