{
  "id": "seasonal-garden-frost-protection-wrap-amyntaio",
  "slug": "epochiaki-prostasia-pagetou-fyton-kipou-amyntaio",
  "nameGr": "Εποχική Προστασία Παγετού Φυτών Κήπου στο Αμύνταιο",
  "nameEn": "Seasonal Garden Frost Protection Wrap in Αμύνταιο",
  "categoryId": "gardeners",
  "categorySlug": "kipouroi",
  "intent": "Εποχική προστασία φυτών κήπου στο Αμύνταιο από παγετό με κατάλληλα καλύμματα και πρακτικές συντήρησης. SEO intent: «προστασία φυτών από παγετό Αμύνταιο».",
  "typicalDuration": "1-4 ώρες",
  "priceRangeEUR": "60-240€",
  "demand": "high",
  "keywords": [
    "προστασία φυτών από παγετό Αμύνταιο",
    "κάλυμμα παγετού κήπου",
    "κηπουρός χειμερινή προστασία",
    "φυτά κρύο ζημιές λύση",
    "seasonal frost wrap service"
  ],
  "status": "researched"
}