{
  "id": "seasonal-roof-gutter-spout-unclog-astrochori",
  "slug": "epochiaki-apofraxi-stomiou-ydroorris-stegis-astrochori",
  "nameGr": "Εποχική Απόφραξη Στομίου Υδρορροής Στέγης στο Αστροχώρι",
  "nameEn": "Seasonal Roof Gutter Spout Unclog in Αστροχώρι",
  "categoryId": "roofing-specialists",
  "categorySlug": "steges-skepes",
  "intent": "Εποχική απόφραξη στομίου υδρορροής στέγης στο Αστροχώρι για άμεση απορροή πριν από έντονες βροχοπτώσεις.",
  "typicalDuration": "30-120 λεπτά",
  "priceRangeEUR": "45-170€",
  "demand": "high",
  "keywords": [
    "Αστροχώρι επείγον",
    "άμεση εξυπηρέτηση",
    "τοπικός τεχνικός",
    "service κατοικίας",
    "επισκευή τώρα"
  ],
  "status": "researched"
}