{
  "id": "seasonal-home-entry-grout-repair-kalabaka-village",
  "slug": "epochiaki-episkevi-armostokou-eisodou-katoikias-kalabaka-village",
  "nameGr": "Εποχική Επισκευή Αρμόστοκου Εισόδου Κατοικίας σε χωριό της Καλαμπάκας",
  "nameEn": "Seasonal Home Entry Grout Repair in Καλαμπάκα",
  "categoryId": "tilers",
  "categorySlug": "plakadades",
  "intent": "Εποχική επισκευή αρμόστοκου στην είσοδο κατοικίας σε χωριό της Καλαμπάκας για πρόληψη υγρασίας και αποκόλλησης πλακιδίων. SEO intent: «αρμόστοκος βγήκε είσοδος Καλαμπάκα».",
  "typicalDuration": "30-120 λεπτά",
  "priceRangeEUR": "45-170€",
  "demand": "high",
  "keywords": [
    "αρμόστοκος βγήκε είσοδος Καλαμπάκα",
    "επισκευή αρμών πλακιδίων εισόδου",
    "πλακάς μικροεπισκευές κατοικίας",
    "πρόληψη υγρασίας δαπέδου",
    "service αρμολόγησης εξωτερικού"
  ],
  "status": "researched"
}