{
  "id": "smart-water-heater-timer-retrofit-thiva",
  "slug": "metatropi-thermosifona-se-smart-chronodiakopti-thiva",
  "nameGr": "Μετατροπή Θερμοσίφωνα σε Smart Χρονοδιακόπτη στη Θήβα",
  "nameEn": "Smart Water Heater Timer Retrofit in Θήβα",
  "categoryId": "electricians",
  "categorySlug": "ilektrologoi",
  "intent": "Μετατροπή θερμοσίφωνα σε smart χρονοδιακόπτη στη Θήβα για έλεγχο από κινητό και εξοικονόμηση ρεύματος. SEO intent: καλύπτει high-intent queries «smart θερμοσίφωνας Θήβα».",
  "typicalDuration": "1-3 ώρες",
  "priceRangeEUR": "80-320€",
  "demand": "high",
  "keywords": [
    "smart χρονοδιακόπτης θερμοσίφωνα Θήβα",
    "έλεγχος θερμοσίφωνα από κινητό",
    "ηλεκτρολόγος smart relay θερμοσίφωνα",
    "μείωση κατανάλωσης θερμοσίφωνα",
    "αυτοματισμός θερμοσίφωνα"
  ],
  "status": "researched"
}