{
  "id": "water-softener-installation-siteia",
  "slug": "egkatastasi-aposklyrynti-nerou-siteia",
  "nameGr": "Εγκατάσταση Αποσκληρυντή Νερού στη Σητεία",
  "nameEn": "Water Softener Installation in Σητεία",
  "categoryId": "plumbers",
  "categorySlug": "ydravlikoi",
  "intent": "Εγκατάσταση αποσκληρυντή νερού στη Σητεία για προστασία σωληνώσεων και συσκευών από άλατα με σωστή ρύθμιση παροχής. SEO intent: στοχεύει εμπορικές αναζητήσεις όπως «αποσκληρυντής νερού Σητεία» και «υδραυλικός εγκατάσταση φίλτρων».",
  "typicalDuration": "2-5 ώρες",
  "priceRangeEUR": "380-1600€",
  "demand": "high",
  "keywords": [
    "αποσκληρυντής νερού Σητεία",
    "εγκατάσταση φίλτρου νερού Σητεία",
    "υδραυλικός για άλατα νερού",
    "προστασία σωληνώσεων από άλατα",
    "σύστημα επεξεργασίας νερού"
  ],
  "status": "researched"
}