{
  "id": "well-water-uv-purification-install-methoni",
  "slug": "egkatastasi-uv-katharismou-nerou-geotrisis-methoni",
  "nameGr": "Εγκατάσταση UV Καθαρισμού Νερού Γεώτρησης στη Μεθώνη",
  "nameEn": "Well Water UV Purification Install in Μεθώνη",
  "categoryId": "plumbers",
  "categorySlug": "ydravlikoi",
  "intent": "Εγκατάσταση UV καθαρισμού νερού γεώτρησης στη Μεθώνη για βελτίωση υγιεινής και ποιότητας χρήσης νερού. SEO intent: καλύπτει αναζητήσεις «UV νερού γεώτρησης Μεθώνη».",
  "typicalDuration": "2-6 ώρες",
  "priceRangeEUR": "260-1200€",
  "demand": "high",
  "keywords": [
    "UV νερού γεώτρησης Μεθώνη",
    "καθαρισμός νερού γεώτρησης",
    "σύστημα απολύμανσης νερού UV",
    "υδραυλικός φίλτρα νερού γεώτρησης",
    "ποιότητα νερού κατοικίας"
  ],
  "status": "researched"
}