[
  {
    "businessName": "ΚΟΥΜΠΟΥΛΗΣ ΤΕΧΝΙΚΗ ΕΤΑΙΡΕΙΑ",
    "phone": "2106009617",
    "city": "Αγία Παρασκευή",
    "source": "vrisko.gr",
    "sourceUrl": "https://www.vrisko.gr/search/%CF%84%CE%B5%CF%87%CE%BD%CE%B9%CE%BA%CE%BF%CE%AF%20%CE%BA%CE%BB%CE%B9%CE%BC%CE%B1%CF%84%CE%B9%CF%83%CE%BC%CE%BF%CF%8D/%CE%97%CF%81%CE%AC%CE%BA%CE%BB%CE%B5%CE%B9%CE%BF/"
  },
  {
    "businessName": "KINTISCLIMA - ΚΙΝΤΗΣ ΔΗΜΗΤΡΗΣ & ΘΕΟΔΟΣΙΟΣ",
    "phone": "6936341760",
    "city": "Αρτέμιδα",
    "source": "vrisko.gr",
    "sourceUrl": "https://www.vrisko.gr/search/%CF%84%CE%B5%CF%87%CE%BD%CE%B9%CE%BA%CE%BF%CE%AF%20%CE%BA%CE%BB%CE%B9%CE%BC%CE%B1%CF%84%CE%B9%CF%83%CE%BC%CE%BF%CF%8D/%CE%97%CF%81%CE%AC%CE%BA%CE%BB%CE%B5%CE%B9%CE%BF/"
  },
  {
    "businessName": "COLDECO - ΜΩΡΑΪΤΗΣ ΣΙΜΟΣ",
    "phone": "6984042976",
    "city": "Άγιος Δημήτριος",
    "source": "vrisko.gr",
    "sourceUrl": "https://www.vrisko.gr/search/%CF%84%CE%B5%CF%87%CE%BD%CE%B9%CE%BA%CE%BF%CE%AF%20%CE%BA%CE%BB%CE%B9%CE%BC%CE%B1%CF%84%CE%B9%CF%83%CE%BC%CE%BF%CF%8D/%CE%97%CF%81%CE%AC%CE%BA%CE%BB%CE%B5%CE%B9%CE%BF/"
  },
  {
    "businessName": "KAFKIAS STEFANOS - AUTO SERVICE - ΚΑΥΚΙΑΣ ΣΤΕΦΑΝΟΣ",
    "phone": "2106754284",
    "city": "Αθήνα",
    "source": "vrisko.gr",
    "sourceUrl": "https://www.vrisko.gr/search/%CE%BA%CE%BB%CE%B9%CE%BC%CE%B1%CF%84%CE%B9%CF%83%CF%84%CE%B9%CE%BA%CE%AC/%CE%91%CE%B8%CE%AE%CE%BD%CE%B1/"
  },
  {
    "businessName": "AIRVACON",
    "phone": "2108620627",
    "city": "Αθήνα",
    "source": "vrisko.gr",
    "sourceUrl": "https://www.vrisko.gr/search/%CE%BA%CE%BB%CE%B9%CE%BC%CE%B1%CF%84%CE%B9%CF%83%CF%84%CE%B9%CE%BA%CE%AC/%CE%91%CE%B8%CE%AE%CE%BD%CE%B1/"
  },
  {
    "businessName": "4SEASONSCLIMA",
    "phone": "6996952378",
    "city": "Αθήνα",
    "source": "vrisko.gr",
    "sourceUrl": "https://www.vrisko.gr/search/%CE%BA%CE%BB%CE%B9%CE%BC%CE%B1%CF%84%CE%B9%CF%83%CF%84%CE%B9%CE%BA%CE%AC/%CE%91%CE%B8%CE%AE%CE%BD%CE%B1/"
  },
  {
    "businessName": "MASTERCLIMA - ΒΕΝΕΚΑΣ ΙΩΑΝΝΗΣ & ΣΙΑ Ε.Ε.",
    "phone": "2105151511",
    "city": "Αθήνα",
    "source": "vrisko.gr",
    "sourceUrl": "https://www.vrisko.gr/search/%CE%BA%CE%BB%CE%B9%CE%BC%CE%B1%CF%84%CE%B9%CF%83%CF%84%CE%B9%CE%BA%CE%AC/%CE%91%CE%B8%CE%AE%CE%BD%CE%B1/"
  },
  {
    "businessName": "CLIMA HDE",
    "phone": "6938455702",
    "city": "Αθήνα",
    "source": "vrisko.gr",
    "sourceUrl": "https://www.vrisko.gr/search/%CE%BA%CE%BB%CE%B9%CE%BC%CE%B1%CF%84%CE%B9%CF%83%CF%84%CE%B9%CE%BA%CE%AC/%CE%91%CE%B8%CE%AE%CE%BD%CE%B1/"
  },
  {
    "businessName": "AEGEANCLIMA - ΔΑΚΤΥΛΙΔΗΣ ΚΩΝΣΤΑΝΤΙΝΟΣ",
    "phone": "2114101834",
    "city": "Αθήνα",
    "source": "vrisko.gr",
    "sourceUrl": "https://www.vrisko.gr/search/%CE%BA%CE%BB%CE%B9%CE%BC%CE%B1%CF%84%CE%B9%CF%83%CF%84%CE%B9%CE%BA%CE%AC/%CE%91%CE%B8%CE%AE%CE%BD%CE%B1/"
  },
  {
    "businessName": "ΣΙΜΟΣ ΚΩΣΤΑΣ",
    "phone": "2106425117",
    "city": "Αθήνα",
    "source": "vrisko.gr",
    "sourceUrl": "https://www.vrisko.gr/search/%CE%BA%CE%BB%CE%B9%CE%BC%CE%B1%CF%84%CE%B9%CF%83%CF%84%CE%B9%CE%BA%CE%AC/%CE%91%CE%B8%CE%AE%CE%BD%CE%B1/"
  },
  {
    "businessName": "POWER COOL - ΖΟΥΜΗΣ ΒΑΣΙΛΗΣ",
    "phone": "2103472225",
    "city": "Αθήνα",
    "source": "vrisko.gr",
    "sourceUrl": "https://www.vrisko.gr/search/%CE%BA%CE%BB%CE%B9%CE%BC%CE%B1%CF%84%CE%B9%CF%83%CF%84%CE%B9%CE%BA%CE%AC/%CE%91%CE%B8%CE%AE%CE%BD%CE%B1/"
  },
  {
    "businessName": "M.P.RADIATORS I.K.E.",
    "phone": "2109022450",
    "city": "Αθήνα",
    "source": "vrisko.gr",
    "sourceUrl": "https://www.vrisko.gr/search/%CE%BA%CE%BB%CE%B9%CE%BC%CE%B1%CF%84%CE%B9%CF%83%CF%84%CE%B9%CE%BA%CE%AC/%CE%91%CE%B8%CE%AE%CE%BD%CE%B1/"
  },
  {
    "businessName": "EXINTARIS SERVICE - ΕΞΗΝΤΑΡΗΣ ΕΥΑΓΓ. ΙΩΑΝΝΗΣ",
    "phone": "2108679333",
    "city": "Αθήνα",
    "source": "vrisko.gr",
    "sourceUrl": "https://www.vrisko.gr/search/%CE%BA%CE%BB%CE%B9%CE%BC%CE%B1%CF%84%CE%B9%CF%83%CF%84%CE%B9%CE%BA%CE%AC/%CE%91%CE%B8%CE%AE%CE%BD%CE%B1/"
  },
  {
    "businessName": "ΚΟΤΑΡΑΚΟΣ ΛΕΩΝΙΔΑΣ",
    "phone": "2104965804",
    "city": "Κορυδαλλός",
    "source": "vrisko.gr",
    "sourceUrl": "https://www.vrisko.gr/search/%CE%BA%CE%BB%CE%B9%CE%BC%CE%B1%CF%84%CE%B9%CF%83%CF%84%CE%B9%CE%BA%CE%AC/%CE%91%CE%B8%CE%AE%CE%BD%CE%B1/"
  },
  {
    "businessName": "PSR",
    "phone": "6948314221",
    "city": "Νίκαια",
    "source": "vrisko.gr",
    "sourceUrl": "https://www.vrisko.gr/search/%CE%BA%CE%BB%CE%B9%CE%BC%CE%B1%CF%84%CE%B9%CF%83%CF%84%CE%B9%CE%BA%CE%AC/%CE%91%CE%B8%CE%AE%CE%BD%CE%B1/"
  },
  {
    "businessName": "ΛΩΛΟΣ FOURSEASONS",
    "phone": "2107628880",
    "city": "Βύρωνας",
    "source": "vrisko.gr",
    "sourceUrl": "https://www.vrisko.gr/search/%CE%BA%CE%BB%CE%B9%CE%BC%CE%B1%CF%84%CE%B9%CF%83%CF%84%CE%B9%CE%BA%CE%AC/%CE%91%CE%B8%CE%AE%CE%BD%CE%B1/"
  },
  {
    "businessName": "AIR ALIFERIS",
    "phone": "2109621627",
    "city": "Αργυρούπολη",
    "source": "vrisko.gr",
    "sourceUrl": "https://www.vrisko.gr/search/%CE%BA%CE%BB%CE%B9%CE%BC%CE%B1%CF%84%CE%B9%CF%83%CF%84%CE%B9%CE%BA%CE%AC/%CE%91%CE%B8%CE%AE%CE%BD%CE%B1/"
  },
  {
    "businessName": "V.S ΤΕΧΝΙΚΗ",
    "phone": "2114108178",
    "city": "Περιστέρι",
    "source": "vrisko.gr",
    "sourceUrl": "https://www.vrisko.gr/search/%CE%BA%CE%BB%CE%B9%CE%BC%CE%B1%CF%84%CE%B9%CF%83%CF%84%CE%B9%CE%BA%CE%AC/%CE%91%CE%B8%CE%AE%CE%BD%CE%B1/"
  },
  {
    "businessName": "DL COOL & CLIMA",
    "phone": "2105752257",
    "city": "Περιστέρι",
    "source": "vrisko.gr",
    "sourceUrl": "https://www.vrisko.gr/search/%CE%BA%CE%BB%CE%B9%CE%BC%CE%B1%CF%84%CE%B9%CF%83%CF%84%CE%B9%CE%BA%CE%AC/%CE%91%CE%B8%CE%AE%CE%BD%CE%B1/"
  },
  {
    "businessName": "ΤΣΕΛΙΟΣ ΘΕΜ. ΑΘΑΝΑΣΙΟΣ - KLIMAHOME Ο.Ε.",
    "phone": "2106744201",
    "city": "Νέο Ψυχικό",
    "source": "vrisko.gr",
    "sourceUrl": "https://www.vrisko.gr/search/%CE%BA%CE%BB%CE%B9%CE%BC%CE%B1%CF%84%CE%B9%CF%83%CF%84%CE%B9%CE%BA%CE%AC/%CE%91%CE%B8%CE%AE%CE%BD%CE%B1/"
  },
  {
    "businessName": "KLIMA EXPRESS Ε.Ε.",
    "phone": "2110124786",
    "city": "Πειραιάς",
    "source": "vrisko.gr",
    "sourceUrl": "https://www.vrisko.gr/search/%CE%BA%CE%BB%CE%B9%CE%BC%CE%B1%CF%84%CE%B9%CF%83%CF%84%CE%B9%CE%BA%CE%AC/%CE%91%CE%B8%CE%AE%CE%BD%CE%B1/"
  },
  {
    "businessName": "ΓΟΥΝΑΡΗΣ Κ. & ΣΙΑ Ο.Ε.",
    "phone": "2107715459",
    "city": "Ζωγράφος",
    "source": "vrisko.gr",
    "sourceUrl": "https://www.vrisko.gr/search/%CE%BA%CE%BB%CE%B9%CE%BC%CE%B1%CF%84%CE%B9%CF%83%CF%84%CE%B9%CE%BA%CE%AC/%CE%91%CE%B8%CE%AE%CE%BD%CE%B1/"
  },
  {
    "businessName": "OPEL ΛΑΖΑΡΟΥ ΕΜΜ. & ΠΕΤ. Ο.Ε. - LAZAROU TUNING",
    "phone": "2109426129",
    "city": "Καλλιθέα",
    "source": "vrisko.gr",
    "sourceUrl": "https://www.vrisko.gr/search/%CE%BA%CE%BB%CE%B9%CE%BC%CE%B1%CF%84%CE%B9%CF%83%CF%84%CE%B9%CE%BA%CE%AC/%CE%91%CE%B8%CE%AE%CE%BD%CE%B1/"
  },
  {
    "businessName": "ANGEL CAR - ΜΠΟΔΙΤΣΟΠΟΥΛΟΣ ΑΓΓΕΛΟΣ",
    "phone": "2316015294",
    "city": "Θεσσαλονίκη",
    "source": "vrisko.gr",
    "sourceUrl": "https://www.vrisko.gr/search/%CE%BA%CE%BB%CE%B9%CE%BC%CE%B1%CF%84%CE%B9%CF%83%CF%84%CE%B9%CE%BA%CE%AC/%CE%98%CE%B5%CF%83%CF%83%CE%B1%CE%BB%CE%BF%CE%BD%CE%AF%CE%BA%CE%B7/"
  },
  {
    "businessName": "ΔΗΜΑΣ ΔΗΜΗΤΡΗΣ",
    "phone": "6943263700",
    "city": "Θεσσαλονίκη",
    "source": "vrisko.gr",
    "sourceUrl": "https://www.vrisko.gr/search/%CE%BA%CE%BB%CE%B9%CE%BC%CE%B1%CF%84%CE%B9%CF%83%CF%84%CE%B9%CE%BA%CE%AC/%CE%98%CE%B5%CF%83%CF%83%CE%B1%CE%BB%CE%BF%CE%BD%CE%AF%CE%BA%CE%B7/"
  },
  {
    "businessName": "ΛΥΚΙΔΗΣ ΑΝΑΣΤΑΣΙΟΣ",
    "phone": "2310323105",
    "city": "Θεσσαλονίκη",
    "source": "vrisko.gr",
    "sourceUrl": "https://www.vrisko.gr/search/%CE%BA%CE%BB%CE%B9%CE%BC%CE%B1%CF%84%CE%B9%CF%83%CF%84%CE%B9%CE%BA%CE%AC/%CE%98%CE%B5%CF%83%CF%83%CE%B1%CE%BB%CE%BF%CE%BD%CE%AF%CE%BA%CE%B7/"
  },
  {
    "businessName": "ΚΑΛΑΪΤΖΙΔΗΣ ΜΕΝΕΛΑΟΣ FROSTY",
    "phone": "2310868144",
    "city": "Θεσσαλονίκη",
    "source": "vrisko.gr",
    "sourceUrl": "https://www.vrisko.gr/search/%CE%BA%CE%BB%CE%B9%CE%BC%CE%B1%CF%84%CE%B9%CF%83%CF%84%CE%B9%CE%BA%CE%AC/%CE%98%CE%B5%CF%83%CF%83%CE%B1%CE%BB%CE%BF%CE%BD%CE%AF%CE%BA%CE%B7/"
  },
  {
    "businessName": "ΠΑΠΑΓΕΩΡΓΟΠΟΥΛΟΣ ΓΕΩΡΓΙΟΣ",
    "phone": "6944551980",
    "city": "Θεσσαλονίκη",
    "source": "vrisko.gr",
    "sourceUrl": "https://www.vrisko.gr/search/%CE%BA%CE%BB%CE%B9%CE%BC%CE%B1%CF%84%CE%B9%CF%83%CF%84%CE%B9%CE%BA%CE%AC/%CE%98%CE%B5%CF%83%CF%83%CE%B1%CE%BB%CE%BF%CE%BD%CE%AF%CE%BA%CE%B7/"
  },
  {
    "businessName": "ΖΑΡΑΓΚΟΥΛΙΑΣ ΦΟΙΒΟΣ",
    "phone": "2310309111",
    "city": "Θεσσαλονίκη",
    "source": "vrisko.gr",
    "sourceUrl": "https://www.vrisko.gr/search/%CE%BA%CE%BB%CE%B9%CE%BC%CE%B1%CF%84%CE%B9%CF%83%CF%84%CE%B9%CE%BA%CE%AC/%CE%98%CE%B5%CF%83%CF%83%CE%B1%CE%BB%CE%BF%CE%BD%CE%AF%CE%BA%CE%B7/"
  },
  {
    "businessName": "ΑΘΑΝΑΣΙΟΥ ΙΩΑΝΝΗΣ",
    "phone": "2314052853",
    "city": "Θεσσαλονίκη",
    "source": "vrisko.gr",
    "sourceUrl": "https://www.vrisko.gr/search/%CE%BA%CE%BB%CE%B9%CE%BC%CE%B1%CF%84%CE%B9%CF%83%CF%84%CE%B9%CE%BA%CE%AC/%CE%98%CE%B5%CF%83%CF%83%CE%B1%CE%BB%CE%BF%CE%BD%CE%AF%CE%BA%CE%B7/"
  },
  {
    "businessName": "KETIKOGLOU - THE CAR COOLING PROJECT",
    "phone": "2316015856",
    "city": "Θεσσαλονίκη",
    "source": "vrisko.gr",
    "sourceUrl": "https://www.vrisko.gr/search/%CE%BA%CE%BB%CE%B9%CE%BC%CE%B1%CF%84%CE%B9%CF%83%CF%84%CE%B9%CE%BA%CE%AC/%CE%98%CE%B5%CF%83%CF%83%CE%B1%CE%BB%CE%BF%CE%BD%CE%AF%CE%BA%CE%B7/"
  },
  {
    "businessName": "ΜΗΧΑΝΟΗΛΕΚΤΡΙΚΗ - ΚΙΛΙΚΙΔΗΣ ΕΥΣΤΡΑΤΙΟΣ",
    "phone": "2310854235",
    "city": "Θεσσαλονίκη",
    "source": "vrisko.gr",
    "sourceUrl": "https://www.vrisko.gr/search/%CE%BA%CE%BB%CE%B9%CE%BC%CE%B1%CF%84%CE%B9%CF%83%CF%84%CE%B9%CE%BA%CE%AC/%CE%98%CE%B5%CF%83%CF%83%CE%B1%CE%BB%CE%BF%CE%BD%CE%AF%CE%BA%CE%B7/"
  },
  {
    "businessName": "ΗΛΕΚΤΡΟΤΕΧΝΙΚΗ - ΚΑΡΑΓΕΩΡΓΟΠΟΥΛΟΣ ΕΥΘΥΜΙΟΣ",
    "phone": "2310848739",
    "city": "Θεσσαλονίκη",
    "source": "vrisko.gr",
    "sourceUrl": "https://www.vrisko.gr/search/%CE%BA%CE%BB%CE%B9%CE%BC%CE%B1%CF%84%CE%B9%CF%83%CF%84%CE%B9%CE%BA%CE%AC/%CE%98%CE%B5%CF%83%CF%83%CE%B1%CE%BB%CE%BF%CE%BD%CE%AF%CE%BA%CE%B7/"
  },
  {
    "businessName": "ΚΛΙΜΑΖΗΝ",
    "phone": "6974090850",
    "city": "Θεσσαλονίκη",
    "source": "vrisko.gr",
    "sourceUrl": "https://www.vrisko.gr/search/%CE%BA%CE%BB%CE%B9%CE%BC%CE%B1%CF%84%CE%B9%CF%83%CF%84%CE%B9%CE%BA%CE%AC/%CE%98%CE%B5%CF%83%CF%83%CE%B1%CE%BB%CE%BF%CE%BD%CE%AF%CE%BA%CE%B7/"
  },
  {
    "businessName": "KLIMA TITAS",
    "phone": "2310220650",
    "city": "Θεσσαλονίκη",
    "source": "vrisko.gr",
    "sourceUrl": "https://www.vrisko.gr/search/%CE%BA%CE%BB%CE%B9%CE%BC%CE%B1%CF%84%CE%B9%CF%83%CF%84%CE%B9%CE%BA%CE%AC/%CE%98%CE%B5%CF%83%CF%83%CE%B1%CE%BB%CE%BF%CE%BD%CE%AF%CE%BA%CE%B7/"
  },
  {
    "businessName": "ELECTROLOGIO.GR",
    "phone": "2310318582",
    "city": "Θεσσαλονίκη",
    "source": "vrisko.gr",
    "sourceUrl": "https://www.vrisko.gr/search/%CE%BA%CE%BB%CE%B9%CE%BC%CE%B1%CF%84%CE%B9%CF%83%CF%84%CE%B9%CE%BA%CE%AC/%CE%98%CE%B5%CF%83%CF%83%CE%B1%CE%BB%CE%BF%CE%BD%CE%AF%CE%BA%CE%B7/"
  },
  {
    "businessName": "ΚΑΠΑ ΠΙ",
    "phone": "2310989545",
    "city": "Πυλαία",
    "source": "vrisko.gr",
    "sourceUrl": "https://www.vrisko.gr/search/%CE%BA%CE%BB%CE%B9%CE%BC%CE%B1%CF%84%CE%B9%CF%83%CF%84%CE%B9%CE%BA%CE%AC/%CE%98%CE%B5%CF%83%CF%83%CE%B1%CE%BB%CE%BF%CE%BD%CE%AF%CE%BA%CE%B7/"
  },
  {
    "businessName": "REAL ENERGY",
    "phone": "2310029669",
    "city": "Καλαμαριά",
    "source": "vrisko.gr",
    "sourceUrl": "https://www.vrisko.gr/search/%CE%BA%CE%BB%CE%B9%CE%BC%CE%B1%CF%84%CE%B9%CF%83%CF%84%CE%B9%CE%BA%CE%AC/%CE%98%CE%B5%CF%83%CF%83%CE%B1%CE%BB%CE%BF%CE%BD%CE%AF%CE%BA%CE%B7/"
  },
  {
    "businessName": "AIRCARE – ΠΕΤΟΓΛΟΥ ΓΕΩΡΓΙΟΣ",
    "phone": "6947822172",
    "city": "Εύοσμος",
    "source": "vrisko.gr",
    "sourceUrl": "https://www.vrisko.gr/search/%CE%BA%CE%BB%CE%B9%CE%BC%CE%B1%CF%84%CE%B9%CF%83%CF%84%CE%B9%CE%BA%CE%AC/%CE%98%CE%B5%CF%83%CF%83%CE%B1%CE%BB%CE%BF%CE%BD%CE%AF%CE%BA%CE%B7/"
  },
  {
    "businessName": "ΚΥΡΜΟΣ ΑΝΤΩΝΗΣ - CLIMAPARK",
    "phone": "6948182736",
    "city": "Ωραιόκαστρο",
    "source": "vrisko.gr",
    "sourceUrl": "https://www.vrisko.gr/search/%CE%BA%CE%BB%CE%B9%CE%BC%CE%B1%CF%84%CE%B9%CF%83%CF%84%CE%B9%CE%BA%CE%AC/%CE%98%CE%B5%CF%83%CF%83%CE%B1%CE%BB%CE%BF%CE%BD%CE%AF%CE%BA%CE%B7/"
  },
  {
    "businessName": "ΠΕΡΣΙΔΟΤΕΧΝΙΚΗ",
    "phone": "2310681833",
    "city": "Ευκαρπία",
    "source": "vrisko.gr",
    "sourceUrl": "https://www.vrisko.gr/search/%CE%BA%CE%BB%CE%B9%CE%BC%CE%B1%CF%84%CE%B9%CF%83%CF%84%CE%B9%CE%BA%CE%AC/%CE%98%CE%B5%CF%83%CF%83%CE%B1%CE%BB%CE%BF%CE%BD%CE%AF%CE%BA%CE%B7/"
  },
  {
    "businessName": "ΝΤΑΓΙΑΜΑΣ ΑΝΑΣΤΑΣΙΟΣ",
    "phone": "6972761742",
    "city": "Νέοι Επιβάτες",
    "source": "vrisko.gr",
    "sourceUrl": "https://www.vrisko.gr/search/%CE%BA%CE%BB%CE%B9%CE%BC%CE%B1%CF%84%CE%B9%CF%83%CF%84%CE%B9%CE%BA%CE%AC/%CE%98%CE%B5%CF%83%CF%83%CE%B1%CE%BB%CE%BF%CE%BD%CE%AF%CE%BA%CE%B7/"
  },
  {
    "businessName": "SUPERCOOL SERVICE - ΓΚΑΛΜΠΕΝΗΣ Σ. ΚΩΣΤΑΣ",
    "phone": "2310760989",
    "city": "Μενεμένη",
    "source": "vrisko.gr",
    "sourceUrl": "https://www.vrisko.gr/search/%CE%BA%CE%BB%CE%B9%CE%BC%CE%B1%CF%84%CE%B9%CF%83%CF%84%CE%B9%CE%BA%CE%AC/%CE%98%CE%B5%CF%83%CF%83%CE%B1%CE%BB%CE%BF%CE%BD%CE%AF%CE%BA%CE%B7/"
  },
  {
    "businessName": "ΣΠΥΡΟΠΟΥΛΟΣ ΠΑΝΑΓΙΩΤΗΣ",
    "phone": "2610438540",
    "city": "Πάτρα",
    "source": "vrisko.gr",
    "sourceUrl": "https://www.vrisko.gr/search/%CE%BA%CE%BB%CE%B9%CE%BC%CE%B1%CF%84%CE%B9%CF%83%CF%84%CE%B9%CE%BA%CE%AC/%CE%A0%CE%AC%CF%84%CF%81%CE%B1/"
  },
  {
    "businessName": "ΑΕΡΑΓΩΓΟΣ Ο.Ε.",
    "phone": "2610580313",
    "city": "Πάτρα",
    "source": "vrisko.gr",
    "sourceUrl": "https://www.vrisko.gr/search/%CE%BA%CE%BB%CE%B9%CE%BC%CE%B1%CF%84%CE%B9%CF%83%CF%84%CE%B9%CE%BA%CE%AC/%CE%A0%CE%AC%CF%84%CF%81%CE%B1/"
  },
  {
    "businessName": "CLIMA TECHNICS - ΝΙΚΟΛΟΠΟΥΛΟΣ N. ΑΓΓΕΛΟΣ",
    "phone": "2610339740",
    "city": "Πάτρα",
    "source": "vrisko.gr",
    "sourceUrl": "https://www.vrisko.gr/search/%CE%BA%CE%BB%CE%B9%CE%BC%CE%B1%CF%84%CE%B9%CF%83%CF%84%CE%B9%CE%BA%CE%AC/%CE%A0%CE%AC%CF%84%CF%81%CE%B1/"
  },
  {
    "businessName": "ΜΠΑΪΛΟΣ CLIMATENERGY",
    "phone": "2610325109",
    "city": "Πάτρα",
    "source": "vrisko.gr",
    "sourceUrl": "https://www.vrisko.gr/search/%CE%BA%CE%BB%CE%B9%CE%BC%CE%B1%CF%84%CE%B9%CF%83%CF%84%CE%B9%CE%BA%CE%AC/%CE%A0%CE%AC%CF%84%CF%81%CE%B1/"
  },
  {
    "businessName": "ΜΕΝΥΧΤΑΣ ΝΙΚΟΛΑΟΣ",
    "phone": "6946223048",
    "city": "Πάτρα",
    "source": "vrisko.gr",
    "sourceUrl": "https://www.vrisko.gr/search/%CE%BA%CE%BB%CE%B9%CE%BC%CE%B1%CF%84%CE%B9%CF%83%CF%84%CE%B9%CE%BA%CE%AC/%CE%A0%CE%AC%CF%84%CF%81%CE%B1/"
  },
  {
    "businessName": "ΜΟΝΟΚΡΟΥΣΟΣ Ι. ΠΑΝΑΓΙΩΤΗΣ",
    "phone": "2610335900",
    "city": "Πάτρα",
    "source": "vrisko.gr",
    "sourceUrl": "https://www.vrisko.gr/search/%CE%BA%CE%BB%CE%B9%CE%BC%CE%B1%CF%84%CE%B9%CF%83%CF%84%CE%B9%CE%BA%CE%AC/%CE%A0%CE%AC%CF%84%CF%81%CE%B1/"
  },
  {
    "businessName": "ΜΠΟΥΓΙΟΥΚΟΣ Ε.Ε. - KRONOS",
    "phone": "2610342520",
    "city": "Πάτρα",
    "source": "vrisko.gr",
    "sourceUrl": "https://www.vrisko.gr/search/%CE%BA%CE%BB%CE%B9%CE%BC%CE%B1%CF%84%CE%B9%CF%83%CF%84%CE%B9%CE%BA%CE%AC/%CE%A0%CE%AC%CF%84%CF%81%CE%B1/"
  }
]